seleniumsearch.py
seleniumsearch-0.0.1.dist-info/WHEEL
seleniumsearch-0.0.1.dist-info/METADATA
seleniumsearch-0.0.1.dist-info/RECORD
