Metadata-Version: 2.1
Name: seleniumsearch
Version: 0.0.1
Summary: Search with selenium
Author: Brodyaga
Requires-Python: >=3.8,<4.0
Classifier: Programming Language :: Python :: 3
Classifier: Programming Language :: Python :: 3.8
Classifier: Programming Language :: Python :: 3.9
Classifier: Programming Language :: Python :: 3.10
Classifier: Programming Language :: Python :: 3.11
